locust_influx/__init__.py
locust_influx-0.2.4.dist-info/LICENSE
locust_influx-0.2.4.dist-info/METADATA
locust_influx-0.2.4.dist-info/WHEEL
locust_influx-0.2.4.dist-info/top_level.txt
locust_influx-0.2.4.dist-info/RECORD
