Metadata-Version: 2.1
Name: locust-influx
Version: 0.2.4
Summary: Report locust metrics to influxdb.
Home-page: https://github.com/lucrib/locust_influx
Author: Lucas Ribeiro
Author-email: lucasribeiro1990@gmail.com
License: Apache-2.0
Project-URL: Documentation, https://locust_influx.github.io
Project-URL: Source, https://github.com/lucrib/locust_influx
Platform: UNKNOWN
Classifier: Development Status :: 4 - Beta
Classifier: Environment :: Plugins
Classifier: Intended Audience :: Developers
Classifier: License :: OSI Approved :: Apache Software License
Classifier: Operating System :: OS Independent
Classifier: Programming Language :: Python :: 3 :: Only
Classifier: Programming Language :: Python :: 3.6
Classifier: Programming Language :: Python :: 3.7
Requires-Python: >=3.6
Requires-Dist: locustio (>=0.12.2)
Requires-Dist: influxdb (>=5.2.2)
